Metadata-Version: 2.1
Name: fairdetect-test
Version: 0.2
Summary: Library to identify bias in pre-trained models!
Home-page: https://github.com/CarlosBlazquezP/test_upload
Author: Carlos Blazquez
Author-email: Carlos.BlazquezP@gmail.com
License: MIT
Platform: UNKNOWN
